python_generate_xlsx_report/__init__.py
python_generate_xlsx_report/src/__init__.py
python_generate_xlsx_report/src/python_generate_xlsx_report.py
python_generate_xlsx_report/test/__init__.py
python_generate_xlsx_report-0.0.10.dist-info/licenses/LICENSE
python_generate_xlsx_report-0.0.10.dist-info/METADATA
python_generate_xlsx_report-0.0.10.dist-info/WHEEL
python_generate_xlsx_report-0.0.10.dist-info/top_level.txt
python_generate_xlsx_report-0.0.10.dist-info/RECORD
