Metadata-Version: 2.4
Name: python_generate_xlsx_report
Version: 0.0.10
Summary: Um gerador de relatório de análise quantitativa e qualitativa
Home-page: https://github.com/DadosComCafe/vigilante
Author: dadoscomcafe
Author-email: dadoscomcafe.dev@gmail.com
License: MIT
Classifier: License :: OSI Approved :: MIT License
Classifier: Programming Language :: Python :: 3.12
Classifier: Operating System :: OS Independent
Requires-Python: >=3.12
License-File: LICENSE
Requires-Dist: openpyxl==3.1.5
Dynamic: author
Dynamic: author-email
Dynamic: classifier
Dynamic: description
Dynamic: description-content-type
Dynamic: home-page
Dynamic: license
Dynamic: license-file
Dynamic: requires-dist
Dynamic: requires-python
Dynamic: summary
